arbitrium/__about__.py
arbitrium/__init__.py
arbitrium/arbitrium.py
arbitrium/py.typed
arbitrium/cli/__init__.py
arbitrium/cli/args.py
arbitrium/cli/main.py
arbitrium/config/__init__.py
arbitrium/config/defaults.py
arbitrium/config/loader.py
arbitrium/core/__init__.py
arbitrium/core/anonymizer.py
arbitrium/core/helpers.py
arbitrium/core/knowledge_bank.py
arbitrium/core/report.py
arbitrium/core/scorer.py
arbitrium/core/tournament.py
arbitrium/core/prompts/__init__.py
arbitrium/core/prompts/builder.py
arbitrium/core/prompts/formatter.py
arbitrium/core/prompts/templates.py
arbitrium/logging/__init__.py
arbitrium/logging/setup.py
arbitrium/logging/structured.py
arbitrium/models/__init__.py
arbitrium/models/base.py
arbitrium/models/factory.py
arbitrium/models/providers.py
arbitrium/models/registry.py
arbitrium/utils/__init__.py
arbitrium/utils/async_.py
arbitrium/utils/constants.py
arbitrium/utils/context_validation.py
arbitrium/utils/display.py
arbitrium/utils/exceptions.py
arbitrium/utils/file.py
arbitrium/utils/json_.py
arbitrium/utils/markdown.py
arbitrium/utils/provenance.py
arbitrium/utils/response_validation.py
arbitrium/utils/secrets.py
arbitrium/utils/terminal.py
arbitrium_framework-0.0.5.dist-info/licenses/LICENSE
arbitrium_framework-0.0.5.dist-info/licenses/NOTICE
arbitrium_framework-0.0.5.dist-info/METADATA
arbitrium_framework-0.0.5.dist-info/WHEEL
arbitrium_framework-0.0.5.dist-info/entry_points.txt
arbitrium_framework-0.0.5.dist-info/top_level.txt
arbitrium_framework-0.0.5.dist-info/RECORD
