Metadata-Version: 2.4
Name: arbitrium-framework
Version: 0.0.5
Summary: Arbitrium Framework: A framework for collaborative-competitive LLM evaluation.
Author-email: Nikolay Eremeev <nikolay.eremeev@outlook.com>
Project-URL: Homepage, https://github.com/arbitrium-framework/arbitrium
Project-URL: Bug Tracker, https://github.com/arbitrium-framework/arbitrium/issues
Project-URL: Repository, https://github.com/arbitrium-framework/arbitrium
Project-URL: Documentation, https://github.com/arbitrium-framework/arbitrium#readme
Classifier: Programming Language :: Python :: 3
Classifier: License :: OSI Approved :: MIT License
Classifier: Operating System :: OS Independent
Requires-Python: >=3.10
License-File: LICENSE
License-File: NOTICE
Requires-Dist: litellm~=1.77.1
Requires-Dist: pyyaml~=6.0
Requires-Dist: colorama~=0.4.6
Requires-Dist: aiohttp~=3.12.0
Requires-Dist: httpx~=0.28.0
Requires-Dist: tiktoken>=0.7.0
Requires-Dist: aiofiles~=24.1.0
Requires-Dist: scikit-learn~=1.7.2
Requires-Dist: markdown-it-py~=4.0
Requires-Dist: google-auth~=2.41
Provides-Extra: bench
Requires-Dist: datasets~=4.2.0; extra == "bench"
Requires-Dist: scipy~=1.12; extra == "bench"
Requires-Dist: pandas~=2.2; extra == "bench"
Provides-Extra: dev
Requires-Dist: pytest~=8.0; extra == "dev"
Requires-Dist: pytest-asyncio~=1.2; extra == "dev"
Requires-Dist: pytest-cov~=7.0; extra == "dev"
Requires-Dist: pytest-xdist~=3.0; extra == "dev"
Requires-Dist: hypothesis~=6.0; extra == "dev"
Requires-Dist: coverage[toml]~=7.0; extra == "dev"
Requires-Dist: black<26.0,>=24.10; extra == "dev"
Requires-Dist: isort<6.0,>=5.13; extra == "dev"
Requires-Dist: ruff<1.0,>=0.6.9; extra == "dev"
Requires-Dist: mypy~=1.11; extra == "dev"
Requires-Dist: types-colorama~=0.4; extra == "dev"
Requires-Dist: types-PyYAML~=6.0; extra == "dev"
Requires-Dist: types-aiofiles~=25.1; extra == "dev"
Requires-Dist: pre-commit~=4.3; extra == "dev"
Requires-Dist: mutmut~=3.3; extra == "dev"
Requires-Dist: radon~=6.0; extra == "dev"
Requires-Dist: import-linter~=2.0; extra == "dev"
Dynamic: license-file
